Test/ReluTest/vhdl/relu-2-11/vhdl/CNN_ReluCore.vhdl
library IEEE;
use IEEE.STD_LOGIC_1164.ALL;
use IEEE.NUMERIC_STD.ALL;

-- library SYSTEM_TYPES;
use work.SYSTEM_TYPES.ALL;
-- library CUSTOM_TYPES;
use work.CUSTOM_TYPES.ALL;

  -- Component declaration and signals

-- User defined packages here
-- #### USER-DATA-IMPORTS-START
-- #### USER-DATA-IMPORTS-END

entity CNN_ReluCore is
    port(
        -- Input bus Input signals
        Input_enable: in T_SYSTEM_BOOL;
        Input_Value: in T_SYSTEM_FLOAT;
        Input_LastValue: in T_SYSTEM_BOOL;

        -- Output bus Output signals
        Output_enable: out T_SYSTEM_BOOL;
        Output_LastValue: out T_SYSTEM_BOOL;
        Output_Value: out T_SYSTEM_FLOAT;

        -- Clock signal
        CLK : in Std_logic;

        -- Ready signal
        RDY : in Std_logic;

        -- Finished signal
        FIN : out Std_logic;

        -- Enable signal
        ENB : in Std_logic;

        -- Reset signal
        RST : in Std_logic
    );
end CNN_ReluCore;

architecture RTL of CNN_ReluCore is 


begin
    process(
        CLK,
        RST
    )
    begin
        if (RST = '1') then
            Output_enable <= '0';
            Output_LastValue <= '0';
            Output_Value <= (others => '0');
            FIN <= '0';
        elsif rising_edge(CLK) then
            Output_enable <= Input_enable;
            Output_LastValue <= '0';
            if (Input_enable = '1') then
                if Input_Value(31) = '0' then
                    Output_Value <= Input_Value;
                else
                    Output_Value <= (others => '0');
                end if;
            else
                Output_Value <= (others => '0');
            end if;
            FIN <= not RDY;
        end if;
    end process;


end RTL;

-- User defined architectures here
-- #### USER-DATA-ARCH-START
-- #### USER-DATA-ARCH-END

Test/ReluTest/vhdl/relu-2-11/vhdl/Relu.vhdl
library IEEE;
use IEEE.STD_LOGIC_1164.ALL;
use IEEE.NUMERIC_STD.ALL;

-- library SYSTEM_TYPES;
use work.SYSTEM_TYPES.ALL;

-- library CUSTOM_TYPES;
use work.CUSTOM_TYPES.ALL;

-- User defined packages here
-- #### USER-DATA-IMPORTS-START
-- #### USER-DATA-IMPORTS-END

entity Relu is
    port(
        -- Top-level bus ValueBus signals
        ValueBus_1_enable: in T_SYSTEM_BOOL;
        ValueBus_1_Value: in T_SYSTEM_FLOAT;
        ValueBus_1_LastValue: in T_SYSTEM_BOOL;

        -- Top-level bus ValueBus signals
        ValueBus_0_enable: out T_SYSTEM_BOOL;
        ValueBus_0_Value: out T_SYSTEM_FLOAT;
        ValueBus_0_LastValue: out T_SYSTEM_BOOL;

        -- User defined signals here
        -- #### USER-DATA-ENTITYSIGNALS-START
        -- #### USER-DATA-ENTITYSIGNALS-END

        -- Enable signal
        ENB : in Std_logic;

        -- Finished signal
        FIN : out Std_logic;

        -- Reset signal
        RST : in Std_logic;

        -- Clock signal
        CLK : in Std_logic
    );
end Relu;

architecture RTL of Relu is

    -- User defined signals here
    -- #### USER-DATA-SIGNALS-START
    -- #### USER-DATA-SIGNALS-END

    -- Process ready triggers
    signal FIN_ReluCore : std_logic;

    -- The primary ready driver signal
    signal RDY : std_logic;

begin

    -- Entity ReluCore signals
    ReluCore: entity work.CNN_ReluCore
    port map (
        -- Input bus ValueBus
        Input_enable => ValueBus_1_enable,
        Input_Value => ValueBus_1_Value,
        Input_LastValue => ValueBus_1_LastValue,

        -- Output bus ValueBus
        Output_enable => ValueBus_0_enable,
        Output_LastValue => ValueBus_0_LastValue,
        Output_Value => ValueBus_0_Value,

        CLK => CLK,
        RDY => RDY,
        FIN => FIN_ReluCore,
        ENB => ENB,
        RST => RST
    );

    -- Connect ready signals

    -- Setup the FIN feedback signals
    FIN <= FIN_ReluCore;

    -- Propagate all clocked and feedback signals
    process(
        CLK,
        RST
    )
        variable readyflag: std_logic;
    begin
        if RST = '1' then
            RDY <= '0';
            readyflag := '0';
        elsif rising_edge(CLK) then
            if ENB = '1' then
                readyflag := not readyflag;
                RDY <= readyflag;
            end if;
        end if;
    end process;

    -- User defined processes here
    -- #### USER-DATA-CODE-START
    -- #### USER-DATA-CODE-END

end RTL;

Test/ReluTest/vhdl/relu-2-11/vhdl/TestBench_Relu.vhdl
library IEEE;
use IEEE.STD_LOGIC_1164.ALL;
use IEEE.NUMERIC_STD.ALL;
use STD.TEXTIO.all;
use IEEE.STD_LOGIC_TEXTIO.all;

--library SYSTEM_TYPES;
use work.SYSTEM_TYPES.ALL;

--library CUSTOM_TYPES;
use work.CUSTOM_TYPES.ALL;

use work.csv_util.all;

-- User defined packages here
-- #### USER-DATA-IMPORTS-START
-- #### USER-DATA-IMPORTS-END

entity Relu_tb is
end;

architecture TestBench of Relu_tb is

    signal CLOCK : Std_logic;
    signal StopClock : BOOLEAN;
    signal RESET : Std_logic;
    signal ENABLE : Std_logic;

    signal ValueBus_0_enable : T_SYSTEM_BOOL;
    signal ValueBus_0_LastValue : T_SYSTEM_BOOL;
    signal ValueBus_0_Value : T_SYSTEM_FLOAT;
    signal ValueBus_1_enable : T_SYSTEM_BOOL;
    signal ValueBus_1_LastValue : T_SYSTEM_BOOL;
    signal ValueBus_1_Value : T_SYSTEM_FLOAT;

begin

    uut: entity work.Relu
    port map (
        ValueBus_1_enable => ValueBus_1_enable,
        ValueBus_1_Value => ValueBus_1_Value,
        ValueBus_1_LastValue => ValueBus_1_LastValue,
        ValueBus_0_enable => ValueBus_0_enable,
        ValueBus_0_Value => ValueBus_0_Value,
        ValueBus_0_LastValue => ValueBus_0_LastValue,

        ENB => ENABLE,
        RST => RESET,
        CLK => CLOCK
    );

    Clk: process
    begin
        while not StopClock loop
            CLOCK <= '1';
            wait for 5 NS;
            CLOCK <= '0';
            wait for 5 NS;
        end loop;
        wait;
    end process;

    TraceFileTester: process

        file F: TEXT;
        variable L: LINE;
        variable Status: FILE_OPEN_STATUS;
        constant filename : string := "../trace.csv";
        variable clockcycle : integer := 0;
        variable tmp : CSV_LINE_T;
        variable readOK : boolean;
        variable fieldno : integer := 0;
        variable failures : integer := 0;
        variable newfailures: integer := 0;
        variable first_failure_tick : integer := -1;
        variable first_round : boolean := true;

    begin

        -- #### USER-DATA-CONDITONING-START
        -- #### USER-DATA-CONDITONING-END

        FILE_OPEN(Status, F, filename, READ_MODE);
        if Status /= OPEN_OK then
            report "Failed to open CSV trace file" severity Failure;
        else
            -- Verify the headers
            READLINE(F, L);

            fieldno := 0;
            read_csv_field(L, tmp);
            assert are_strings_equal(tmp, "ValueBus#1.enable") report "Field #" & integer'image(fieldno) & " is not correctly named: " & truncate(tmp) & ", expected ValueBus#1.enable" severity Failure;
            fieldno := fieldno + 1;
            read_csv_field(L, tmp);
            assert are_strings_equal(tmp, "ValueBus#1.LastValue") report "Field #" & integer'image(fieldno) & " is not correctly named: " & truncate(tmp) & ", expected ValueBus#1.LastValue" severity Failure;
            fieldno := fieldno + 1;
            read_csv_field(L, tmp);
            assert are_strings_equal(tmp, "ValueBus#1.Value") report "Field #" & integer'image(fieldno) & " is not correctly named: " & truncate(tmp) & ", expected ValueBus#1.Value" severity Failure;
            fieldno := fieldno + 1;
            read_csv_field(L, tmp);
            assert are_strings_equal(tmp, "ValueBus#0.enable") report "Field #" & integer'image(fieldno) & " is not correctly named: " & truncate(tmp) & ", expected ValueBus#0.enable" severity Failure;
            fieldno := fieldno + 1;
            read_csv_field(L, tmp);
            assert are_strings_equal(tmp, "ValueBus#0.LastValue") report "Field #" & integer'image(fieldno) & " is not correctly named: " & truncate(tmp) & ", expected ValueBus#0.LastValue" severity Failure;
            fieldno := fieldno + 1;
            read_csv_field(L, tmp);
            assert are_strings_equal(tmp, "ValueBus#0.Value") report "Field #" & integer'image(fieldno) & " is not correctly named: " & truncate(tmp) & ", expected ValueBus#0.Value" severity Failure;
            fieldno := fieldno + 1;

            RESET <= '1';
            ENABLE <= '0';
            wait for 5 NS;
            RESET <= '0';
            ENABLE <= '1';

            -- Read a line each clock
            while not ENDFILE(F) loop
                READLINE(F, L);
                fieldno := 0;
                newfailures := 0;

                -- Write all driver signals out on the clock edge,
                -- except on the first round, where we make sure the reset
                -- values are propagated _before_ the initial clock edge
                if not first_round then
                    wait until rising_edge(CLOCK);
                end if;

                read_csv_field(L, tmp);
                if are_strings_equal(tmp, "U") then
                    ValueBus_1_enable <= 'U';
                else
                    ValueBus_1_enable <= to_std_logic(truncate(tmp));
                end if;
                fieldno := fieldno + 1;
                read_csv_field(L, tmp);
                if are_strings_equal(tmp, "U") then
                    ValueBus_1_LastValue <= 'U';
                else
                    ValueBus_1_LastValue <= to_std_logic(truncate(tmp));
                end if;
                fieldno := fieldno + 1;
                read_csv_field(L, tmp);
                if are_strings_equal(tmp, "U") then
                    ValueBus_1_Value <= (others => 'U');
                else
                    ValueBus_1_Value <= to_std_logic_vector(truncate(tmp));
                end if;
                fieldno := fieldno + 1;

                if first_round then
                    first_round := false;
                else
                    -- Wait until the signals are settled before veriying the results
                    wait until falling_edge(CLOCK);
                end if;

                -- Compare each signal with the value in the CSV file
                read_csv_field(L, tmp);
                if not are_strings_equal(tmp, "U") then
                    if not are_strings_equal(str(ValueBus_0_enable), tmp) then
                        newfailures := newfailures + 1;
                        report "Value for ValueBus_0_enable in cycle " & integer'image(clockcycle) & " was: " & str(ValueBus_0_enable) & " but should have been: " & truncate(tmp) severity Error;
                    end if;
                end if;
                fieldno := fieldno + 1;
                read_csv_field(L, tmp);
                if not are_strings_equal(tmp, "U") then
                    if not are_strings_equal(str(ValueBus_0_LastValue), tmp) then
                        newfailures := newfailures + 1;
                        report "Value for ValueBus_0_LastValue in cycle " & integer'image(clockcycle) & " was: " & str(ValueBus_0_LastValue) & " but should have been: " & truncate(tmp) severity Error;
                    end if;
                end if;
                fieldno := fieldno + 1;
                read_csv_field(L, tmp);
                if not are_strings_equal(tmp, "U") then
                    if not are_strings_equal(str(ValueBus_0_Value), tmp) then
                        newfailures := newfailures + 1;
                        report "Value for ValueBus_0_Value in cycle " & integer'image(clockcycle) & " was: " & str(ValueBus_0_Value) & " but should have been: " & truncate(tmp) severity Error;
                    end if;
                end if;
                fieldno := fieldno + 1;

                failures := failures + newfailures;
                if newfailures = 0 then
                    first_failure_tick := -1;
                elsif first_failure_tick = -1 then
                    first_failure_tick := clockcycle;
                else
                    if clockcycle - first_failure_tick >= 5 then
                        report "Stopping simulation due to five consecutive failed cycles" severity error;
                        StopClock <= true;
                    elsif failures > 20 then
                        report "Stopping simulation after 20 failures" severity error;
                        StopClock <= true;
                    end if;
                end if;

                clockcycle := clockcycle + 1;
            end loop;

            FILE_CLOSE(F);
        end if;

        if failures = 0 then
            report "completed successfully after " & integer'image(clockcycle) & " clockcycles";
        else
            report "completed with " & integer'image(failures) & " error(s) after " & integer'image(clockcycle) & " clockcycle(s)";
        end if;
        StopClock <= true;

        wait;
    end process;
end architecture TestBench;

Test/ReluTest/vhdl/relu-2-11/vhdl/trace.vcd
$date
  Sat Aug 12 14:15:06 2023
$end
$version
  GHDL v0
$end
$timescale
  1 fs
$end
$scope module standard $end
$upscope $end
$scope module std_logic_1164 $end
$upscope $end
$scope module numeric_std $end
$upscope $end
$scope module textio $end
$upscope $end
$scope module std_logic_textio $end
$upscope $end
$scope module system_types $end
$upscope $end
$scope module custom_types $end
$upscope $end
$scope module csv_util $end
$upscope $end
$scope module relu_tb $end
$var reg 1 ! clock $end
$var reg 1 " stopclock $end
$var reg 1 # reset $end
$var reg 1 $ enable $end
$var reg 1 % valuebus_0_enable $end
$var reg 1 & valuebus_0_lastvalue $end
$var reg 32 ' valuebus_0_value[31:0] $end
$var reg 1 ( valuebus_1_enable $end
$var reg 1 ) valuebus_1_lastvalue $end
$var reg 32 * valuebus_1_value[31:0] $end
$scope module uut $end
$var reg 1 + valuebus_1_enable $end
$var reg 32 , valuebus_1_value[31:0] $end
$var reg 1 - valuebus_1_lastvalue $end
$var reg 1 . valuebus_0_enable $end
$var reg 32 / valuebus_0_value[31:0] $end
$var reg 1 0 valuebus_0_lastvalue $end
$var reg 1 1 enb $end
$var reg 1 2 fin $end
$var reg 1 3 rst $end
$var reg 1 4 clk $end
$var reg 1 5 fin_relucore $end
$var reg 1 6 rdy $end
$scope module relucore $end
$var reg 1 7 input_enable $end
$var reg 32 8 input_value[31:0] $end
$var reg 1 9 input_lastvalue $end
$var reg 1 : output_enable $end
$var reg 1 ; output_lastvalue $end
$var reg 32 < output_value[31:0] $end
$var reg 1 = clk $end
$var reg 1 > rdy $end
$var reg 1 ? fin $end
$var reg 1 @ enb $end
$var reg 1 A rst $end
$upscope $end
$upscope $end
$upscope $end
$enddefinitions $end
#0
1!
0"
1#
0$
0%
0&
b00000000000000000000000000000000 '
U(
U)
bUUUUUUUUUUUUUUUUUUUUUUUUUUUUUUUU *
U+
bUUUUUUUUUUUUUUUUUUUUUUUUUUUUUUUU ,
U-
0.
b00000000000000000000000000000000 /
00
01
02
13
14
05
06
U7
bUUUUUUUUUUUUUUUUUUUUUUUUUUUUUUUU 8
U9
0:
0;
b00000000000000000000000000000000 <
1=
0>
0?
0@
1A
#5000000
0!
0#
1$
0(
0)
b00000000000000000000000000000000 *
0+
b00000000000000000000000000000000 ,
0-
11
03
04
07
b00000000000000000000000000000000 8
09
0=
1@
0A
#10000000
1!
1(
b10111110011000010110000001010111 *
1+
b10111110011000010110000001010111 ,
12
14
15
16
17
b10111110011000010110000001010111 8
1=
1>
1?
#15000000
0!
04
0=
#20000000
1!
1%
b00111111101110100001001101001101 *
b00111111101110100001001101001101 ,
1.
02
14
05
06
b00111111101110100001001101001101 8
1:
1=
0>
0?
#25000000
0!
04
0=
#30000000
1!
b00111111101110100001001101001101 '
b00111111110110101011111111110011 *
b00111111110110101011111111110011 ,
b00111111101110100001001101001101 /
12
14
15
16
b00111111110110101011111111110011 8
b00111111101110100001001101001101 <
1=
1>
1?
#35000000
0!
04
0=
#40000000
1!
b00111111110110101011111111110011 '
b00111111001001110000110001010001 *
b00111111001001110000110001010001 ,
b00111111110110101011111111110011 /
02
14
05
06
b00111111001001110000110001010001 8
b00111111110110101011111111110011 <
1=
0>
0?
#45000000
0!
04
0=
#50000000
1!
b00111111001001110000110001010001 '
b10111111001111111101101001110001 *
b10111111001111111101101001110001 ,
b00111111001001110000110001010001 /
12
14
15
16
b10111111001111111101101001110001 8
b00111111001001110000110001010001 <
1=
1>
1?
#55000000
0!
04
0=
#60000000
1!
b00000000000000000000000000000000 '
b00111101100001000011001001000111 *
b00111101100001000011001001000111 ,
b00000000000000000000000000000000 /
02
14
05
06
b00111101100001000011001001000111 8
b00000000000000000000000000000000 <
1=
0>
0?
#65000000
0!
04
0=
#70000000
1!
b00111101100001000011001001000111 '
b10111111010001000000001001100110 *
b10111111010001000000001001100110 ,
b00111101100001000011001001000111 /
12
14
15
16
b10111111010001000000001001100110 8
b00111101100001000011001001000111 <
1=
1>
1?
#75000000
0!
04
0=
#80000000
1!
b00000000000000000000000000000000 '
b10111111100111000111010100000010 *
b10111111100111000111010100000010 ,
b00000000000000000000000000000000 /
02
14
05
06
b10111111100111000111010100000010 8
b00000000000000000000000000000000 <
1=
0>
0?
#85000000
0!
04
0=
#90000000
1!
b10111110101110110110101001100001 *
b10111110101110110110101001100001 ,
12
14
15
16
b10111110101110110110101001100001 8
1=
1>
1?
#95000000
0!
04
0=
#100000000
1!
b10111111000111100010000100001000 *
b10111111000111100010000100001000 ,
02
14
05
06
b10111111000111100010000100001000 8
1=
0>
0?
#105000000
0!
04
0=
#110000000
1!
b10111111110111001111110011100100 *
b10111111110111001111110011100100 ,
12
14
15
16
b10111111110111001111110011100100 8
1=
1>
1?
#115000000
0!
04
0=
#120000000
1!
b10111111110000011000111100011110 *
b10111111110000011000111100011110 ,
02
14
05
06
b10111111110000011000111100011110 8
1=
0>
0?
#125000000
0!
04
0=
#130000000
1!
b10111111111001010000011000110100 *
b10111111111001010000011000110100 ,
12
14
15
16
b10111111111001010000011000110100 8
1=
1>
1?
#135000000
0!
04
0=
#140000000
1!
b00111111010011111011011111111010 *
b00111111010011111011011111111010 ,
02
14
05
06
b00111111010011111011011111111010 8
1=
0>
0?
#145000000
0!
04
0=
#150000000
1!
b00111111010011111011011111111010 '
b00111110101000001010011101100011 *
b00111110101000001010011101100011 ,
b00111111010011111011011111111010 /
12
14
15
16
b00111110101000001010011101100011 8
b00111111010011111011011111111010 <
1=
1>
1?
#155000000
0!
04
0=
#160000000
1!
b00111110101000001010011101100011 '
b11000000000011100000000011111100 *
b11000000000011100000000011111100 ,
b00111110101000001010011101100011 /
02
14
05
06
b11000000000011100000000011111100 8
b00111110101000001010011101100011 <
1=
0>
0?
#165000000
0!
04
0=
#170000000
1!
b00000000000000000000000000000000 '
b10111111110001000010001101011101 *
b10111111110001000010001101011101 ,
b00000000000000000000000000000000 /
12
14
15
16
b10111111110001000010001101011101 8
b00000000000000000000000000000000 <
1=
1>
1?
#175000000
0!
04
0=
#180000000
1!
b10111111000001101100111010011010 *
b10111111000001101100111010011010 ,
02
14
05
06
b10111111000001101100111010011010 8
1=
0>
0?
#185000000
0!
04
0=
#190000000
1!
b10111111101101101100000011011111 *
b10111111101101101100000011011111 ,
12
14
15
16
b10111111101101101100000011011111 8
1=
1>
1?
#195000000
0!
04
0=
#200000000
1!
b10111110010100001011011011000000 *
b10111110010100001011011011000000 ,
02
14
05
06
b10111110010100001011011011000000 8
1=
0>
0?
#205000000
0!
04
0=
#210000000
1!
b00111111000010111101100010011111 *
b00111111000010111101100010011111 ,
12
14
15
16
b00111111000010111101100010011111 8
1=
1>
1?
#215000000
0!
04
0=
#220000000
1!
b00111111000010111101100010011111 '
b00111110100101011110110100011001 *
b00111110100101011110110100011001 ,
b00111111000010111101100010011111 /
02
14
05
06
b00111110100101011110110100011001 8
b00111111000010111101100010011111 <
1=
0>
0?
#225000000
0!
04
0=
#230000000
1!
b00111110100101011110110100011001 '
b01000000000110101111000010100001 *
b01000000000110101111000010100001 ,
b00111110100101011110110100011001 /
12
14
15
16
b01000000000110101111000010100001 8
b00111110100101011110110100011001 <
1=
1>
1?
#235000000
0!
04
0=
#240000000
1!
b01000000000110101111000010100001 '
b00111111010101101000100011001100 *
b00111111010101101000100011001100 ,
b01000000000110101111000010100001 /
02
14
05
06
b00111111010101101000100011001100 8
b01000000000110101111000010100001 <
1=
0>
0?
#245000000
0!
04
0=
#250000000
1!
b00111111010101101000100011001100 '
b10111111101011001000101001111110 *
b10111111101011001000101001111110 ,
b00111111010101101000100011001100 /
12
14
15
16
b10111111101011001000101001111110 8
b00111111010101101000100011001100 <
1=
1>
1?
#255000000
0!
04
0=
#260000000
1!
b00000000000000000000000000000000 '
b10111111100101110110001101111011 *
b10111111100101110110001101111011 ,
b00000000000000000000000000000000 /
02
14
05
06
b10111111100101110110001101111011 8
b00000000000000000000000000000000 <
1=
0>
0?
#265000000
0!
04
0=
#270000000
1!
b10111110111000011101100100101101 *
b10111110111000011101100100101101 ,
12
14
15
16
b10111110111000011101100100101101 8
1=
1>
1?
#275000000
0!
04
0=
#280000000
1!
b10111110110100101001001110110000 *
b10111110110100101001001110110000 ,
02
14
05
06
b10111110110100101001001110110000 8
1=
0>
0?
#285000000
0!
04
0=
#290000000
1!
b00111111010100001111100010010011 *
b00111111010100001111100010010011 ,
12
14
15
16
b00111111010100001111100010010011 8
1=
1>
1?
#295000000
0!
04
0=
#300000000
1!
b00111111010100001111100010010011 '
b00111111101000111100010110100000 *
b00111111101000111100010110100000 ,
b00111111010100001111100010010011 /
02
14
05
06
b00111111101000111100010110100000 8
b00111111010100001111100010010011 <
1=
0>
0?
#305000000
0!
04
0=
#310000000
1!
b00111111101000111100010110100000 '
b00111111110100110001001011101000 *
b00111111110100110001001011101000 ,
b00111111101000111100010110100000 /
12
14
15
16
b00111111110100110001001011101000 8
b00111111101000111100010110100000 <
1=
1>
1?
#315000000
0!
04
0=
#320000000
1!
b00111111110100110001001011101000 '
b00111111110010101001100001100101 *
b00111111110010101001100001100101 ,
b00111111110100110001001011101000 /
02
14
05
06
b00111111110010101001100001100101 8
b00111111110100110001001011101000 <
1=
0>
0?
#325000000
0!
04
0=
#330000000
1!
b00111111110010101001100001100101 '
b10111111001110011111110011001101 *
b10111111001110011111110011001101 ,
b00111111110010101001100001100101 /
12
14
15
16
b10111111001110011111110011001101 8
b00111111110010101001100001100101 <
1=
1>
1?
#335000000
0!
04
0=
#340000000
1!
b00000000000000000000000000000000 '
b10111111101101000001100101001001 *
b10111111101101000001100101001001 ,
b00000000000000000000000000000000 /
02
14
05
06
b10111111101101000001100101001001 8
b00000000000000000000000000000000 <
1=
0>
0?
#345000000
0!
04
0=
#350000000
1!
b10111111010011010000100100011111 *
b10111111010011010000100100011111 ,
12
14
15
16
b10111111010011010000100100011111 8
1=
1>
1?
#355000000
0!
04
0=
#360000000
1!
b10111110100110001101010000100011 *
b10111110100110001101010000100011 ,
02
14
05
06
b10111110100110001101010000100011 8
1=
0>
0?
#365000000
0!
04
0=
#370000000
1!
b10111101101111111111010101000110 *
b10111101101111111111010101000110 ,
12
14
15
16
b10111101101111111111010101000110 8
1=
1>
1?
#375000000
0!
04
0=
#380000000
1!
b00111111000101111011010010110010 *
b00111111000101111011010010110010 ,
02
14
05
06
b00111111000101111011010010110010 8
1=
0>
0?
#385000000
0!
04
0=
#390000000
1!
b00111111000101111011010010110010 '
b00111111100110101100010010010011 *
b00111111100110101100010010010011 ,
b00111111000101111011010010110010 /
12
14
15
16
b00111111100110101100010010010011 8
b00111111000101111011010010110010 <
1=
1>
1?
#395000000
0!
04
0=
#400000000
1!
b00111111100110101100010010010011 '
b01000000001011000110000110001000 *
b01000000001011000110000110001000 ,
b00111111100110101100010010010011 /
02
14
05
06
b01000000001011000110000110001000 8
b00111111100110101100010010010011 <
1=
0>
0?
#405000000
0!
04
0=
#410000000
1!
b01000000001011000110000110001000 '
b10111110101110111000001011011101 *
b10111110101110111000001011011101 ,
b01000000001011000110000110001000 /
12
14
15
16
b10111110101110111000001011011101 8
b01000000001011000110000110001000 <
1=
1>
1?
#415000000
0!
04
0=
#420000000
1!
b00000000000000000000000000000000 '
b10111111101111011011000001001010 *
b10111111101111011011000001001010 ,
b00000000000000000000000000000000 /
02
14
05
06
b10111111101111011011000001001010 8
b00000000000000000000000000000000 <
1=
0>
0?
#425000000
0!
04
0=
#430000000
1!
b10111111010110011111001001110100 *
b10111111010110011111001001110100 ,
12
14
15
16
b10111111010110011111001001110100 8
1=
1>
1?
#435000000
0!
04
0=
#440000000
1!
b10111111001100000010001000110110 *
b10111111001100000010001000110110 ,
02
14
05
06
b10111111001100000010001000110110 8
1=
0>
0?
#445000000
0!
04
0=
#450000000
1!
b10111110111000111001110001101011 *
b10111110111000111001110001101011 ,
12
14
15
16
b10111110111000111001110001101011 8
1=
1>
1?
#455000000
0!
04
0=
#460000000
1!
b10111111010000001111000110001111 *
b10111111010000001111000110001111 ,
02
14
05
06
b10111111010000001111000110001111 8
1=
0>
0?
#465000000
0!
04
0=
#470000000
1!
b10111111001000011001101111000010 *
b10111111001000011001101111000010 ,
12
14
15
16
b10111111001000011001101111000010 8
1=
1>
1?
#475000000
0!
04
0=
#480000000
1!
b00111111100001011011010110110001 *
b00111111100001011011010110110001 ,
02
14
05
06
b00111111100001011011010110110001 8
1=
0>
0?
#485000000
0!
04
0=
#490000000
1!
b00111111100001011011010110110001 '
b00111110000010100011010111101000 *
b00111110000010100011010111101000 ,
b00111111100001011011010110110001 /
12
14
15
16
b00111110000010100011010111101000 8
b00111111100001011011010110110001 <
1=
1>
1?
#495000000
0!
04
0=
#500000000
1!
b00111110000010100011010111101000 '
b10111111101111110011111000111101 *
b10111111101111110011111000111101 ,
b00111110000010100011010111101000 /
02
14
05
06
b10111111101111110011111000111101 8
b00111110000010100011010111101000 <
1=
0>
0?
#505000000
0!
04
0=
#510000000
1!
b00000000000000000000000000000000 '
b10111111001000010000100110111001 *
b10111111001000010000100110111001 ,
b00000000000000000000000000000000 /
12
14
15
16
b10111111001000010000100110111001 8
b00000000000000000000000000000000 <
1=
1>
1?
#515000000
0!
04
0=
#520000000
1!
b10111100110011011100001100000101 *
b10111100110011011100001100000101 ,
02
14
05
06
b10111100110011011100001100000101 8
1=
0>
0?
#525000000
0!
04
0=
#530000000
1!
b00111110011010100001001111110001 *
b00111110011010100001001111110001 ,
12
14
15
16
b00111110011010100001001111110001 8
1=
1>
1?
#535000000
0!
04
0=
#540000000
1!
b00111110011010100001001111110001 '
b00111111000000010011000000111100 *
b00111111000000010011000000111100 ,
b00111110011010100001001111110001 /
02
14
05
06
b00111111000000010011000000111100 8
b00111110011010100001001111110001 <
1=
0>
0?
#545000000
0!
04
0=
#550000000
1!
b00111111000000010011000000111100 '
b10111111011010000101000110110110 *
b10111111011010000101000110110110 ,
b00111111000000010011000000111100 /
12
14
15
16
b10111111011010000101000110110110 8
b00111111000000010011000000111100 <
1=
1>
1?
#555000000
0!
04
0=
#560000000
1!
b00000000000000000000000000000000 '
b00111110011101011111001101010001 *
b00111110011101011111001101010001 ,
b00000000000000000000000000000000 /
02
14
05
06
b00111110011101011111001101010001 8
b00000000000000000000000000000000 <
1=
0>
0?
#565000000
0!
04
0=
#570000000
1!
b00111110011101011111001101010001 '
b00111111001101000101101101010111 *
b00111111001101000101101101010111 ,
b00111110011101011111001101010001 /
12
14
15
16
b00111111001101000101101101010111 8
b00111110011101011111001101010001 <
1=
1>
1?
#575000000
0!
04
0=
#580000000
1!
b00111111001101000101101101010111 '
b10111111101001111001100100011101 *
b10111111101001111001100100011101 ,
b00111111001101000101101101010111 /
02
14
05
06
b10111111101001111001100100011101 8
b00111111001101000101101101010111 <
1=
0>
0?
#585000000
0!
04
0=
#590000000
1!
b00000000000000000000000000000000 '
b10111111011111010011000001001110 *
b10111111011111010011000001001110 ,
b00000000000000000000000000000000 /
12
14
15
16
b10111111011111010011000001001110 8
b00000000000000000000000000000000 <
1=
1>
1?
#595000000
0!
04
0=
#600000000
1!
b00111110101110101011111111010001 *
b00111110101110101011111111010001 ,
02
14
05
06
b00111110101110101011111111010001 8
1=
0>
0?
#605000000
0!
04
0=
#610000000
1!
b00111110101110101011111111010001 '
b00111111101101001010000101110101 *
b00111111101101001010000101110101 ,
b00111110101110101011111111010001 /
12
14
15
16
b00111111101101001010000101110101 8
b00111110101110101011111111010001 <
1=
1>
1?
#615000000
0!
04
0=
#620000000
1!
b00111111101101001010000101110101 '
b00111111110010000111100011000000 *
b00111111110010000111100011000000 ,
b00111111101101001010000101110101 /
02
14
05
06
b00111111110010000111100011000000 8
b00111111101101001010000101110101 <
1=
0>
0?
#625000000
0!
04
0=
#630000000
1!
b00111111110010000111100011000000 '
b01000000000110000110111010010010 *
b01000000000110000110111010010010 ,
b00111111110010000111100011000000 /
12
14
15
16
b01000000000110000110111010010010 8
b00111111110010000111100011000000 <
1=
1>
1?
#635000000
0!
04
0=
#640000000
1!
b01000000000110000110111010010010 '
b10111111100111101110011110001001 *
b10111111100111101110011110001001 ,
b01000000000110000110111010010010 /
02
14
05
06
b10111111100111101110011110001001 8
b01000000000110000110111010010010 <
1=
0>
0?
#645000000
0!
04
0=
#650000000
1!
b00000000000000000000000000000000 '
b00111111100110101101000000101101 *
b00111111100110101101000000101101 ,
b00000000000000000000000000000000 /
12
14
15
16
b00111111100110101101000000101101 8
b00000000000000000000000000000000 <
1=
1>
1?
#655000000
0!
04
0=
#660000000
1!
b00111111100110101101000000101101 '
b00111111111110011111111010110001 *
b00111111111110011111111010110001 ,
b00111111100110101101000000101101 /
02
14
05
06
b00111111111110011111111010110001 8
b00111111100110101101000000101101 <
1=
0>
0?
#665000000
0!
04
0=
#670000000
1!
b00111111111110011111111010110001 '
b10111110010010110100010111001000 *
b10111110010010110100010111001000 ,
b00111111111110011111111010110001 /
12
14
15
16
b10111110010010110100010111001000 8
b00111111111110011111111010110001 <
1=
1>
1?
#675000000
0!
04
0=
#680000000
1!
b00000000000000000000000000000000 '
b00111110100101011001110010010100 *
b00111110100101011001110010010100 ,
b00000000000000000000000000000000 /
02
14
05
06
b00111110100101011001110010010100 8
b00000000000000000000000000000000 <
1=
0>
0?
#685000000
0!
04
0=
#690000000
1!
b00111110100101011001110010010100 '
b00111110111101111111111100000000 *
b00111110111101111111111100000000 ,
b00111110100101011001110010010100 /
12
14
15
16
b00111110111101111111111100000000 8
b00111110100101011001110010010100 <
1=
1>
1?
#695000000
0!
04
0=
#700000000
1!
b00111110111101111111111100000000 '
b00111111011111111110101001110010 *
b00111111011111111110101001110010 ,
b00111110111101111111111100000000 /
02
14
05
06
b00111111011111111110101001110010 8
b00111110111101111111111100000000 <
1=
0>
0?
#705000000
0!
04
0=
#710000000
1!
b00111111011111111110101001110010 '
b00111111111000001000011100111111 *
b00111111111000001000011100111111 ,
b00111111011111111110101001110010 /
12
14
15
16
b00111111111000001000011100111111 8
b00111111011111111110101001110010 <
1=
1>
1?
#715000000
0!
04
0=
#720000000
1!
b00111111111000001000011100111111 '
b00111111010111101010011001010010 *
b00111111010111101010011001010010 ,
b00111111111000001000011100111111 /
02
14
05
06
b00111111010111101010011001010010 8
b00111111111000001000011100111111 <
1=
0>
0?
#725000000
0!
04
0=
#730000000
1!
b00111111010111101010011001010010 '
b10111111100001110110010111110010 *
b10111111100001110110010111110010 ,
b00111111010111101010011001010010 /
12
14
15
16
b10111111100001110110010111110010 8
b00111111010111101010011001010010 <
1=
1>
1?
#735000000
0!
04
0=
#740000000
1!
b00000000000000000000000000000000 '
b00111111111110001010001111011110 *
b00111111111110001010001111011110 ,
b00000000000000000000000000000000 /
02
14
05
06
b00111111111110001010001111011110 8
b00000000000000000000000000000000 <
1=
0>
0?
#745000000
0!
04
0=
